README.md
setup.py
nsosurveytools/BasicGuiProgram.py
nsosurveytools/RandomTable.pkl
nsosurveytools/__init__.py
nsosurveytools/agrisurvey - Copy (2).py
nsosurveytools/agrisurvey - Copy (3).py
nsosurveytools/agrisurvey - Copy.py
nsosurveytools/agrisurvey.py
nsosurveytools/agrisurvey.spec.txt
nsosurveytools/cmdd.py
nsosurveytools/gui.py
nsosurveytools/hello_world.py
nsosurveytools/nsosurveytoolsUpdate.txt
nsosurveytools/tkstdout.py
nsosurveytools/untitled3.py
nsosurveytools.egg-info/PKG-INFO
nsosurveytools.egg-info/SOURCES.txt
nsosurveytools.egg-info/dependency_links.txt
nsosurveytools.egg-info/entry_points.txt
nsosurveytools.egg-info/requires.txt
nsosurveytools.egg-info/top_level.txt