Metadata-Version: 2.1
Name: nsosurveytools
Version: 1.4
Summary:  Tools To Save Time 
Home-page: https://github.com/superuser789/surveytools/
Author: Nitin Singh
Author-email: acc4nitin@gmail.com
License: MIT
Platform: UNKNOWN
Classifier: License :: OSI Approved :: MIT License
Classifier: Programming Language :: Python :: 3
Classifier: Programming Language :: Python :: 3.7
